MANIFEST.in
README
README.rst
setup.py
./djtracker/__init__.py
./djtracker/admin.py
./djtracker/forms.py
./djtracker/models.py
./djtracker/urls.py
./djtracker/utils.py
./djtracker/views.py
./djtracker/management/__init__.py
./djtracker/management/commands/__init__.py
./djtracker/management/commands/git_poller.py
./djtracker/management/commands/svn_poller.py
./djtracker/templatetags/__init__.py
./djtracker/templatetags/get_objects.py
./exampleapp/__init__.py
./exampleapp/manage.py
./exampleapp/settings.py
./exampleapp/urls.py
djtracker.egg-info/PKG-INFO
djtracker.egg-info/SOURCES.txt
djtracker.egg-info/dependency_links.txt
djtracker.egg-info/requires.txt
djtracker.egg-info/top_level.txt
djtracker/fixtures/initial_data.json
djtracker/templates/djtracker/base.html
djtracker/templates/djtracker/index.html
djtracker/templates/djtracker/issue_detail.html
djtracker/templates/djtracker/issue_filter.html
djtracker/templates/djtracker/issue_view_all.html
djtracker/templates/djtracker/login.html
djtracker/templates/djtracker/logout.html
djtracker/templates/djtracker/modifier_view.html
djtracker/templates/djtracker/modify_issue.html
djtracker/templates/djtracker/project_index.html
djtracker/templates/djtracker/search_results.html
djtracker/templates/djtracker/submit_issue.html
djtracker/templates/djtracker/upload_form.html
djtracker/templates/djtracker/user_dashboard.html
djtracker/templates/djtracker/user_list.html
djtracker/templates/djtracker/user_profile.html
djtracker/templates/registration/activate.html
djtracker/templates/registration/activation_email.txt
djtracker/templates/registration/activation_email_subject.txt
djtracker/templates/registration/registration_complete.html
djtracker/templates/registration/registration_form.html