Metadata-Version: 1.0
Name: djtracker
Version: 0.3
Summary: An issue tracker built with django
Home-page: http://www.f4ntasmic.com
Author: Mark Rogers
Author-email: f4nt@f4ntasmic.com
License: BSD License
Keywords: django issue tracker
Platform: UNKNOWN
Classifier: Intended Audience :: Developers
Classifier: License :: OSI Approved :: BSD License
Classifier: Programming Language :: Python
